[
	{
		"name": "Brazil",
		"leaderName": "Pedru II",
		"adjective": ["Brazilian"],
		"startBias": ["jungles"],
		"preferredVictoryType": "Diplomatic",
		
		"startIntroPart1": "Welcome to Brazil!",
		"startIntroPart2": "Hail to Pedro II!",
		
		"declaringWar": "We are ready to fight!",
		"attacked": "We defend our homeland!",
		"defeated": "We're still alive.",
		"introduction": "We are here.",
		
		"neutralHello": "How are you doing?",
		"neutralLetsHearIt": ["Go on.","What do you say?","You may begin."],
		"neutralNo": ["We absolutely refuse.","No!","I refuse."],
		"neutralYes": ["Very good.","Of course, yes.","That is very good."],

		"hateHello": "What do you want now?",
		"hateLetsHearIt": ["Speak!","What do you say?","Go on."],
		"hateNo": ["That is not possible!","We are not agreeing to that!","I beg your pardon?"],
		"hateYes": ["That is fine.","That is good enough.","Very well..."],
		
		"afterPeace": "Very well, all that fighting was getting boring anyway.",
		"tradeRequest": "We bestow you the honor of this trade offer.",

		"outerColor": [16,16,16],
		"innerColor": [255,200,200],
		"unique": "MANIFEST_DESTINY",
		"cities": ["Rio de Janeiro", "São Paulo", "Brasilia", "Salvador"]
	}
]
